{"attributes":{},"nodes":[{"key":"250","attributes":{"label":"Jeu dématérialisé","x":-1.1408122777938843,"y":-4.9872236251831055,"slug":"jeu-dematerialise","type":"tag"}},{"key":"244","attributes":{"label":"Un peu de Contexte - Le marché du jeu sur PC : Steam et Epic","x":-0.7634559869766235,"y":-1.1399128437042236,"slug":"un-peu-de-contexte-le-marche-du-jeu-sur-pc-steam-et-epic","type":"ressource"}},{"key":"171","attributes":{"label":"Industrie","x":7.658663749694824,"y":-0.7939520478248596,"slug":"industrie","type":"tag"}},{"key":"222","attributes":{"label":"Fortnite","x":-3.333277702331543,"y":7.302309989929199,"slug":"fortnite","type":"tag"}},{"key":"231","attributes":{"label":"Ex Serv","x":0.05847581475973129,"y":7.532482147216797,"slug":"ex-serv","type":"author"}},{"key":"235","attributes":{"label":"Epic Games","x":-4.638424396514893,"y":4.62143087387085,"slug":"epic-games","type":"tag"}},{"key":"245","attributes":{"label":"Valve","x":6.519253730773926,"y":-3.6908838748931885,"slug":"valve","type":"tag"}},{"key":"246","attributes":{"label":"Steam","x":4.414004325866699,"y":-5.912472248077393,"slug":"steam","type":"tag"}},{"key":"247","attributes":{"label":"Epic Games Store","x":1.4221371412277222,"y":-7.799483776092529,"slug":"epic-games-store","type":"tag"}},{"key":"248","attributes":{"label":"Boutique en ligne","x":6.046962738037109,"y":5.184685230255127,"slug":"boutique-en-ligne","type":"tag"}},{"key":"249","attributes":{"label":"Marché PC","x":3.1988940238952637,"y":6.798671722412109,"slug":"marche-pc","type":"tag"}},{"key":"251","attributes":{"label":"Mode de consommation","x":-4.908583164215088,"y":-6.216986179351807,"slug":"mode-de-consommation","type":"tag"}},{"key":"252","attributes":{"label":"Monopole","x":-7.160315036773682,"y":3.101165771484375,"slug":"monopole","type":"tag"}},{"key":"253","attributes":{"label":"Unity","x":6.737399578094482,"y":2.10147762298584,"slug":"unity","type":"tag"}},{"key":"254","attributes":{"label":"Unreal Engine","x":-7.41276741027832,"y":-0.16217947006225586,"slug":"unreal-engine","type":"tag"}},{"key":"255","attributes":{"label":"Steam Greenlight","x":-6.67093563079834,"y":-3.1544275283813477,"slug":"steam-greenlight","type":"tag"}}],"edges":[{"source":"250","target":"244"},{"source":"244","target":"171"},{"source":"244","target":"222"},{"source":"244","target":"231"},{"source":"244","target":"235"},{"source":"244","target":"245"},{"source":"244","target":"246"},{"source":"244","target":"247"},{"source":"244","target":"248"},{"source":"244","target":"249"},{"source":"244","target":"250"},{"source":"244","target":"251"},{"source":"244","target":"252"},{"source":"244","target":"253"},{"source":"244","target":"254"},{"source":"244","target":"255"}],"options":{"type":"mixed","multi":false,"allowSelfLoops":true}}