{"attributes":{},"nodes":[{"key":"28","attributes":{"label":"God of War","x":-5.17788553237915,"y":4.623917579650879,"slug":"god-of-war","type":"tag"}},{"key":"12","attributes":{"label":"Ce qui rend la fantasy Witcher si Humaine","x":6.267988681793213,"y":-10.804190635681152,"slug":"ce-qui-rend-la-fantasy-witcher-si-humaine","type":"ressource"}},{"key":"1","attributes":{"label":"Nostalgeek","x":-1.2325029373168945,"y":4.4410858154296875,"slug":"nostalgeek","type":"author"}},{"key":"3","attributes":{"label":"Bioshock 2","x":13.69190788269043,"y":-12.141182899475098,"slug":"bioshock-2","type":"tag"}},{"key":"13","attributes":{"label":"The Witcher","x":-1.170319676399231,"y":-11.258761405944824,"slug":"the-witcher","type":"tag"}},{"key":"14","attributes":{"label":"The Witcher 3: Wild Hunt","x":2.5589749813079834,"y":-17.55815887451172,"slug":"the-witcher-3-wild-hunt","type":"tag"}},{"key":"15","attributes":{"label":"Andrzej Sapkowski","x":16.76724624633789,"y":-11.65390396118164,"slug":"andrzej-sapkowski","type":"tag"}},{"key":"16","attributes":{"label":"Moralité","x":-0.3972069323062897,"y":-18.340970993041992,"slug":"moralite","type":"tag"}},{"key":"17","attributes":{"label":"Héroïsme","x":8.49863338470459,"y":-21.5242977142334,"slug":"heroisme","type":"tag"}},{"key":"18","attributes":{"label":"Hight fantasy","x":3.48524808883667,"y":-21.107872009277344,"slug":"hight-fantasy","type":"tag"}},{"key":"19","attributes":{"label":"Low fantasy","x":-1.167779564857483,"y":-14.875415802001953,"slug":"low-fantasy","type":"tag"}},{"key":"20","attributes":{"label":"Le Seigneur des Anneaux","x":12.903704643249512,"y":-19.510896682739258,"slug":"le-seigneur-des-anneaux","type":"tag"}},{"key":"21","attributes":{"label":"Open world","x":13.240721702575684,"y":-6.033402442932129,"slug":"open-world","type":"tag"}},{"key":"22","attributes":{"label":"Paternité","x":15.195300102233887,"y":-8.428645133972168,"slug":"paternite","type":"tag"}},{"key":"23","attributes":{"label":"Maternité","x":6.098829746246338,"y":-19.037425994873047,"slug":"maternite","type":"tag"}},{"key":"24","attributes":{"label":"Univers","x":15.787910461425781,"y":-15.747577667236328,"slug":"univers","type":"tag"}},{"key":"25","attributes":{"label":"Neil Gaiman","x":12.531116485595703,"y":-15.968055725097656,"slug":"neil-gaiman","type":"tag"}},{"key":"26","attributes":{"label":"The Last of Us","x":-1.5501937866210938,"y":7.649572849273682,"slug":"the-last-of-us","type":"tag"}},{"key":"27","attributes":{"label":"Dishonored","x":9.99081039428711,"y":-4.471385955810547,"slug":"dishonored","type":"tag"}},{"key":"29","attributes":{"label":"Death Stranding","x":9.663543701171875,"y":-18.24915313720703,"slug":"death-stranding","type":"tag"}},{"key":"165","attributes":{"label":"Remakes & Remasters, bons ou mauvais ?","x":-14.087503433227539,"y":23.291635513305664,"slug":"remakes-remasters-bons-ou-mauvais","type":"ressource"}},{"key":"11","attributes":{"label":"Folie","x":-22.62480926513672,"y":17.22411346435547,"slug":"folie","type":"tag"}},{"key":"34","attributes":{"label":"Dark Souls","x":-25.176069259643555,"y":21.078420639038086,"slug":"dark-souls","type":"tag"}},{"key":"78","attributes":{"label":"Level design","x":-19.29908561706543,"y":16.037578582763672,"slug":"level-design","type":"tag"}},{"key":"88","attributes":{"label":"Remaster","x":-22.577007293701172,"y":24.676288604736328,"slug":"remaster","type":"tag"}},{"key":"93","attributes":{"label":"Remake","x":-15.246947288513184,"y":15.398954391479492,"slug":"remake","type":"tag"}},{"key":"110","attributes":{"label":"Direction artistique","x":-5.011763095855713,"y":24.90373992919922,"slug":"direction-artistique","type":"tag"}},{"key":"148","attributes":{"label":"Modèle économique","x":-5.60228967666626,"y":27.882701873779297,"slug":"modele-economique","type":"tag"}},{"key":"149","attributes":{"label":"Industrie","x":-22.02620506286621,"y":20.406522750854492,"slug":"industrie","type":"tag"}},{"key":"166","attributes":{"label":"Reboot","x":-18.09956932067871,"y":31.02313995361328,"slug":"reboot","type":"tag"}},{"key":"167","attributes":{"label":"Demon's souls","x":-19.43121337890625,"y":34.045127868652344,"slug":"demons-souls","type":"tag"}},{"key":"168","attributes":{"label":"Gameplay","x":-14.10368824005127,"y":31.897075653076172,"slug":"gameplay","type":"tag"}},{"key":"169","attributes":{"label":"Microtransaction","x":-25.723495483398438,"y":24.95896339416504,"slug":"microtransaction","type":"tag"}},{"key":"170","attributes":{"label":"Shadow of the Colossus","x":-21.144580841064453,"y":28.467893600463867,"slug":"shadow-of-the-colossus","type":"tag"}},{"key":"171","attributes":{"label":"Nostalgie","x":-8.783472061157227,"y":33.59156799316406,"slug":"nostalgie","type":"tag"}},{"key":"172","attributes":{"label":"Ni no kuni","x":-15.903958320617676,"y":34.96855545043945,"slug":"ni-no-kuni","type":"tag"}},{"key":"173","attributes":{"label":"Graphisme","x":-9.89996337890625,"y":30.467281341552734,"slug":"graphisme","type":"tag"}},{"key":"174","attributes":{"label":"Call of Duty","x":-6.270545482635498,"y":30.83536720275879,"slug":"call-of-duty","type":"tag"}},{"key":"175","attributes":{"label":"Skyrim","x":-6.158290863037109,"y":21.33589744567871,"slug":"skyrim","type":"tag"}},{"key":"176","attributes":{"label":"Resident Evil 2","x":-12.149223327636719,"y":34.745243072509766,"slug":"resident-evil-2","type":"tag"}},{"key":"177","attributes":{"label":"Ghost Recon","x":-22.391307830810547,"y":31.801925659179688,"slug":"ghost-recon","type":"tag"}},{"key":"178","attributes":{"label":"The Legend of Zelda: Link's Awakening","x":-24.625268936157227,"y":28.62144660949707,"slug":"the-legend-of-zelda-links-awakening","type":"tag"}}],"edges":[{"source":"28","target":"12"},{"source":"12","target":"1"},{"source":"12","target":"3"},{"source":"12","target":"13"},{"source":"12","target":"14"},{"source":"12","target":"15"},{"source":"12","target":"16"},{"source":"12","target":"17"},{"source":"12","target":"18"},{"source":"12","target":"19"},{"source":"12","target":"20"},{"source":"12","target":"21"},{"source":"12","target":"22"},{"source":"12","target":"23"},{"source":"12","target":"24"},{"source":"12","target":"25"},{"source":"12","target":"26"},{"source":"12","target":"27"},{"source":"12","target":"28"},{"source":"12","target":"29"},{"source":"28","target":"165"},{"source":"165","target":"1"},{"source":"165","target":"11"},{"source":"165","target":"26"},{"source":"165","target":"28"},{"source":"165","target":"34"},{"source":"165","target":"78"},{"source":"165","target":"88"},{"source":"165","target":"93"},{"source":"165","target":"110"},{"source":"165","target":"148"},{"source":"165","target":"149"},{"source":"165","target":"166"},{"source":"165","target":"167"},{"source":"165","target":"168"},{"source":"165","target":"169"},{"source":"165","target":"170"},{"source":"165","target":"171"},{"source":"165","target":"172"},{"source":"165","target":"173"},{"source":"165","target":"174"},{"source":"165","target":"175"},{"source":"165","target":"176"},{"source":"165","target":"177"},{"source":"165","target":"178"}],"options":{"type":"mixed","multi":false,"allowSelfLoops":true}}