{"attributes":{},"nodes":[{"key":"216","attributes":{"label":"Prix","x":6.889695167541504,"y":-2.291517972946167,"slug":"prix","type":"tag","pagerank":0.0011964260545279785,"size":5}},{"key":"215","attributes":{"label":"Pourquoi le Prix des jeux va (probablement) Augmenter","x":-3.027921199798584,"y":-0.5475072860717773,"slug":"pourquoi-le-prix-des-jeux-va-probablement-augmenter","type":"ressource","pagerank":0.03291412967202707,"size":19}},{"key":"1","attributes":{"label":"NostalGeek","x":-6.044865131378174,"y":-7.7587456703186035,"slug":"nostalgeek","type":"author","pagerank":0.02024519580639863,"size":13}},{"key":"14","attributes":{"label":"The Witcher 3: Wild Hunt","x":-2.2461094856262207,"y":-9.511569023132324,"slug":"the-witcher-3-wild-hunt","type":"tag","pagerank":0.0019710697840738794,"size":5}},{"key":"28","attributes":{"label":"God of War","x":1.2448424100875854,"y":-12.609959602355957,"slug":"god-of-war","type":"tag","pagerank":0.002704049773887727,"size":6}},{"key":"62","attributes":{"label":"Monétisation","x":4.456486701965332,"y":10.834932327270508,"slug":"monetisation","type":"tag","pagerank":0.002139048574850916,"size":5}},{"key":"77","attributes":{"label":"Loot box","x":1.5516256093978882,"y":12.050973892211914,"slug":"loot-box","type":"tag","pagerank":0.002139048574850916,"size":5}},{"key":"97","attributes":{"label":"Pay to win","x":-1.6010552644729614,"y":11.927602767944336,"slug":"pay-to-win","type":"tag","pagerank":0.002139048574850916,"size":5}},{"key":"103","attributes":{"label":"Marketing","x":-12.819510459899902,"y":-3.1041362285614014,"slug":"marketing","type":"tag","pagerank":0.0027338075548231744,"size":6}},{"key":"107","attributes":{"label":"Sony","x":-10.978997230529785,"y":-7.0065460205078125,"slug":"sony","type":"tag","pagerank":0.005775126563644436,"size":7}},{"key":"125","attributes":{"label":"Triple A","x":-8.622480392456055,"y":-9.468759536743164,"slug":"triple-a","type":"tag","pagerank":0.0043534633918176305,"size":6}},{"key":"156","attributes":{"label":"Naughty Dog","x":-9.222552299499512,"y":-4.616673946380615,"slug":"naughty-dog","type":"tag","pagerank":0.002727768857478413,"size":6}},{"key":"212","attributes":{"label":"Histoire","x":-10.400671005249023,"y":7.139312744140625,"slug":"histoire","type":"tag","pagerank":0.0028483543061261917,"size":6}},{"key":"217","attributes":{"label":"Modèle économique","x":9.278426170349121,"y":-8.542500495910645,"slug":"modele-economique","type":"tag","pagerank":0.002738115906789006,"size":6}},{"key":"218","attributes":{"label":"Industrie","x":4.936177730560303,"y":-11.932254791259766,"slug":"industrie","type":"tag","pagerank":0.004417660454698244,"size":6}},{"key":"219","attributes":{"label":"Cyberpunk 2077","x":2.0012497901916504,"y":-9.43598461151123,"slug":"cyberpunk-2077","type":"tag","pagerank":0.0019796187077529346,"size":5}},{"key":"220","attributes":{"label":"CD Projekt Red","x":10.297959327697754,"y":5.634397983551025,"slug":"cd-projekt-red","type":"tag","pagerank":0.0019727507465717572,"size":5}},{"key":"221","attributes":{"label":"Red Dead Redemption 2","x":8.763630867004395,"y":8.587835311889648,"slug":"red-dead-redemption-2","type":"tag","pagerank":0.0011964260545279785,"size":5}},{"key":"222","attributes":{"label":"Rockstar Games","x":-9.275398254394531,"y":4.0411376953125,"slug":"rockstar-games","type":"tag","pagerank":0.0019610626138474242,"size":5}},{"key":"223","attributes":{"label":"The Last of Us Part II","x":-9.944365501403809,"y":-1.0624396800994873,"slug":"the-last-of-us-part-ii","type":"tag","pagerank":0.0019610626138474242,"size":5}},{"key":"224","attributes":{"label":"Coût de développement","x":-4.826275825500488,"y":11.208130836486816,"slug":"cout-de-developpement","type":"tag","pagerank":0.0011964260545279785,"size":5}},{"key":"225","attributes":{"label":"Shawn Layden","x":-12.616764068603516,"y":3.9375455379486084,"slug":"shawn-layden","type":"tag","pagerank":0.0011964260545279785,"size":5}},{"key":"226","attributes":{"label":"Durée de jeu","x":5.606864929199219,"y":-9.032339096069336,"slug":"duree-de-jeu","type":"tag","pagerank":0.0011964260545279785,"size":5}},{"key":"227","attributes":{"label":"Contenu","x":-2.662649631500244,"y":8.579731941223145,"slug":"contenu","type":"tag","pagerank":0.0011964260545279785,"size":5}},{"key":"228","attributes":{"label":"Ubisoft","x":6.91793155670166,"y":-6.516551971435547,"slug":"ubisoft","type":"tag","pagerank":0.0011964260545279785,"size":5}},{"key":"229","attributes":{"label":"Quêtes secondaires","x":5.760473728179932,"y":8.296642303466797,"slug":"quetes-secondaires","type":"tag","pagerank":0.0011964260545279785,"size":5}},{"key":"230","attributes":{"label":"Grind","x":1.42204749584198,"y":8.512982368469238,"slug":"grind","type":"tag","pagerank":0.0011964260545279785,"size":5}},{"key":"231","attributes":{"label":"Assassin's Creed","x":10.821147918701172,"y":2.796492099761963,"slug":"assassins-creed","type":"tag","pagerank":0.0011964260545279785,"size":5}},{"key":"232","attributes":{"label":"Santa Monica Studio","x":-8.188197135925293,"y":9.874711990356445,"slug":"santa-monica-studio","type":"tag","pagerank":0.0011964260545279785,"size":5}},{"key":"233","attributes":{"label":"NieR Automata","x":10.069138526916504,"y":-0.5499332547187805,"slug":"nier-automata","type":"tag","pagerank":0.0011964260545279785,"size":5}},{"key":"234","attributes":{"label":"Qualité","x":11.552181243896484,"y":-4.929055213928223,"slug":"qualite","type":"tag","pagerank":0.0011964260545279785,"size":5}},{"key":"235","attributes":{"label":"Éditeur de jeux vidéo","x":7.0011444091796875,"y":4.806167125701904,"slug":"editeur-de-jeux-video","type":"tag","pagerank":0.0011964260545279785,"size":5}},{"key":"236","attributes":{"label":"Time saver","x":12.840317726135254,"y":-0.25052410364151,"slug":"time-saver","type":"tag","pagerank":0.0011964260545279785,"size":5}},{"key":"237","attributes":{"label":"Live service","x":-5.574682712554932,"y":-11.415081024169922,"slug":"live-service","type":"tag","pagerank":0.002031417636122042,"size":5}},{"key":"238","attributes":{"label":"Microtransaction","x":-2.178898811340332,"y":-12.751958847045898,"slug":"microtransaction","type":"tag","pagerank":0.001929406044341826,"size":5}},{"key":"239","attributes":{"label":"Cory Barlog","x":-6.396953582763672,"y":7.329487323760986,"slug":"cory-barlog","type":"tag","pagerank":0.0011964260545279785,"size":5}},{"key":"240","attributes":{"label":"Crunch","x":-12.459319114685059,"y":0.8355368375778198,"slug":"crunch","type":"tag","pagerank":0.0019610626138474242,"size":5}}],"edges":[{"source":"216","target":"215"},{"source":"215","target":"1"},{"source":"215","target":"14"},{"source":"215","target":"28"},{"source":"215","target":"62"},{"source":"215","target":"77"},{"source":"215","target":"97"},{"source":"215","target":"103"},{"source":"215","target":"107"},{"source":"215","target":"125"},{"source":"215","target":"156"},{"source":"215","target":"212"},{"source":"215","target":"216"},{"source":"215","target":"217"},{"source":"215","target":"218"},{"source":"215","target":"219"},{"source":"215","target":"220"},{"source":"215","target":"221"},{"source":"215","target":"222"},{"source":"215","target":"223"},{"source":"215","target":"224"},{"source":"215","target":"225"},{"source":"215","target":"226"},{"source":"215","target":"227"},{"source":"215","target":"228"},{"source":"215","target":"229"},{"source":"215","target":"230"},{"source":"215","target":"231"},{"source":"215","target":"232"},{"source":"215","target":"233"},{"source":"215","target":"234"},{"source":"215","target":"235"},{"source":"215","target":"236"},{"source":"215","target":"237"},{"source":"215","target":"238"},{"source":"215","target":"239"},{"source":"215","target":"240"}],"options":{"type":"mixed","multi":false,"allowSelfLoops":true}}