{"attributes":{},"nodes":[{"key":"89","attributes":{"label":"PlayerUnknown's Battlegrounds","x":8.32063102722168,"y":0.6654582023620605,"slug":"playerunknowns-battlegrounds","type":"tag","pagerank":0.0013219723251297242,"size":5}},{"key":"59","attributes":{"label":"Comment le LOOT a CONTAMINÉ le JEU VIDÉO","x":-1.3871569633483887,"y":-1.5951728820800781,"slug":"comment-le-loot-a-contamine-le-jeu-video","type":"ressource","pagerank":0.04519625330182844,"size":25}},{"key":"56","attributes":{"label":"Action RPG","x":-3.9373974800109863,"y":10.365877151489258,"slug":"action-rpg","type":"tag","pagerank":0.005152887059237635,"size":7}},{"key":"60","attributes":{"label":"Game Next Door","x":11.688271522521973,"y":2.3026702404022217,"slug":"game-next-door","type":"author","pagerank":0.0013219723251297242,"size":5}},{"key":"61","attributes":{"label":"Loot","x":5.991738796234131,"y":9.494961738586426,"slug":"loot","type":"tag","pagerank":0.0013219723251297242,"size":5}},{"key":"62","attributes":{"label":"Monétisation","x":8.437418937683105,"y":-7.051063060760498,"slug":"monetisation","type":"tag","pagerank":0.0020620521058115847,"size":5}},{"key":"63","attributes":{"label":"Game design","x":-12.109869003295898,"y":5.417572975158691,"slug":"game-design","type":"tag","pagerank":0.0028909035907042696,"size":6}},{"key":"64","attributes":{"label":"Récompense extrinsèque","x":8.041618347167969,"y":6.555044651031494,"slug":"recompense-extrinseque","type":"tag","pagerank":0.0013219723251297242,"size":5}},{"key":"65","attributes":{"label":"Diablo","x":8.253349304199219,"y":11.838516235351562,"slug":"diablo","type":"tag","pagerank":0.0021036501145267374,"size":5}},{"key":"66","attributes":{"label":"Diablo 2","x":-11.277054786682129,"y":-6.569971561431885,"slug":"diablo-2","type":"tag","pagerank":0.0021036501145267374,"size":5}},{"key":"67","attributes":{"label":"David Brevik","x":-2.906805992126465,"y":-13.599823951721191,"slug":"david-brevik","type":"tag","pagerank":0.0013219723251297242,"size":5}},{"key":"68","attributes":{"label":"Blizzard Entertainment","x":-0.6404350399971008,"y":-10.870645523071289,"slug":"blizzard-entertainment","type":"tag","pagerank":0.0013219723251297242,"size":5}},{"key":"69","attributes":{"label":"Aléatoire","x":9.403606414794922,"y":-10.471872329711914,"slug":"aleatoire","type":"tag","pagerank":0.0013219723251297242,"size":5}},{"key":"70","attributes":{"label":"Burrhus Frederic Skinner","x":6.447930812835693,"y":-10.5264892578125,"slug":"burrhus-frederic-skinner","type":"tag","pagerank":0.0013219723251297242,"size":5}},{"key":"71","attributes":{"label":"Boîte de Skinner","x":-9.656454086303711,"y":-9.538694381713867,"slug":"boite-de-skinner","type":"tag","pagerank":0.0013219723251297242,"size":5}},{"key":"72","attributes":{"label":"Rétention","x":-9.087177276611328,"y":2.2928261756896973,"slug":"retention","type":"tag","pagerank":0.0013219723251297242,"size":5}},{"key":"73","attributes":{"label":"Dopamine","x":-9.8355712890625,"y":8.588438987731934,"slug":"dopamine","type":"tag","pagerank":0.0013219723251297242,"size":5}},{"key":"74","attributes":{"label":"Addiction","x":-13.128769874572754,"y":-0.8344172239303589,"slug":"addiction","type":"tag","pagerank":0.0013219723251297242,"size":5}},{"key":"75","attributes":{"label":"Éthique","x":-11.981547355651855,"y":-3.6547112464904785,"slug":"ethique","type":"tag","pagerank":0.0013219723251297242,"size":5}},{"key":"76","attributes":{"label":"World of Warcraft","x":-0.7613363862037659,"y":9.596356391906738,"slug":"world-of-warcraft","type":"tag","pagerank":0.0013219723251297242,"size":5}},{"key":"77","attributes":{"label":"Loot box","x":13.088953971862793,"y":5.450750350952148,"slug":"loot-box","type":"tag","pagerank":0.0020620521058115847,"size":5}},{"key":"78","attributes":{"label":"Borderlands","x":-6.741943836212158,"y":-8.58221435546875,"slug":"borderlands","type":"tag","pagerank":0.0013219723251297242,"size":5}},{"key":"79","attributes":{"label":"Looter shooter Destiny","x":4.686779975891113,"y":-13.374322891235352,"slug":"looter-shooter-destiny","type":"tag","pagerank":0.0013219723251297242,"size":5}},{"key":"80","attributes":{"label":"Bungie","x":11.946405410766602,"y":-7.682542324066162,"slug":"bungie","type":"tag","pagerank":0.0013219723251297242,"size":5}},{"key":"81","attributes":{"label":"Activision Blizzard","x":3.049151659011841,"y":-10.529067039489746,"slug":"activision-blizzard","type":"tag","pagerank":0.0013219723251297242,"size":5}},{"key":"82","attributes":{"label":"Season pass","x":0.8829925656318665,"y":-13.811969757080078,"slug":"season-pass","type":"tag","pagerank":0.0013219723251297242,"size":5}},{"key":"83","attributes":{"label":"Rogue lite","x":13.890716552734375,"y":-4.2791876792907715,"slug":"rogue-lite","type":"tag","pagerank":0.0013219723251297242,"size":5}},{"key":"84","attributes":{"label":"Hades","x":-12.470417022705078,"y":2.170161008834839,"slug":"hades","type":"tag","pagerank":0.0013219723251297242,"size":5}},{"key":"85","attributes":{"label":"Rareté","x":14.66230297088623,"y":1.1349488496780396,"slug":"rarete","type":"tag","pagerank":0.0013219723251297242,"size":5}},{"key":"86","attributes":{"label":"Renouvellement","x":12.265993118286133,"y":-1.196094036102295,"slug":"renouvellement","type":"tag","pagerank":0.0013219723251297242,"size":5}},{"key":"87","attributes":{"label":"Battle royale","x":-8.067240715026855,"y":-5.01345682144165,"slug":"battle-royale","type":"tag","pagerank":0.0013219723251297242,"size":5}},{"key":"88","attributes":{"label":"Fortnite","x":0.7504380941390991,"y":12.907530784606934,"slug":"fortnite","type":"tag","pagerank":0.004682447316734039,"size":7}},{"key":"90","attributes":{"label":"Apex Legends","x":4.084881782531738,"y":13.054837226867676,"slug":"apex-legends","type":"tag","pagerank":0.0013219723251297242,"size":5}},{"key":"91","attributes":{"label":"Gashapon","x":-8.468242645263672,"y":5.527185440063477,"slug":"gashapon","type":"tag","pagerank":0.0013219723251297242,"size":5}},{"key":"92","attributes":{"label":"Gacha","x":10.256134033203125,"y":-3.944600820541382,"slug":"gacha","type":"tag","pagerank":0.0013219723251297242,"size":5}},{"key":"93","attributes":{"label":"Fifa","x":-7.165102958679199,"y":11.200766563415527,"slug":"fifa","type":"tag","pagerank":0.0013219723251297242,"size":5}},{"key":"94","attributes":{"label":"Valve","x":10.457311630249023,"y":8.629672050476074,"slug":"valve","type":"tag","pagerank":0.0021917737765826464,"size":6}},{"key":"95","attributes":{"label":"Team Fortress 2","x":-9.352906227111816,"y":-1.2884576320648193,"slug":"team-fortress-2","type":"tag","pagerank":0.0013219723251297242,"size":5}},{"key":"96","attributes":{"label":"Counter-Strike","x":-5.87553071975708,"y":7.72028112411499,"slug":"counter-strike","type":"tag","pagerank":0.0013219723251297242,"size":5}},{"key":"97","attributes":{"label":"Pay to win","x":-6.137020111083984,"y":-12.21512222290039,"slug":"pay-to-win","type":"tag","pagerank":0.0020620521058115847,"size":5}},{"key":"98","attributes":{"label":"Shadow of War","x":-3.621086359024048,"y":-9.461610794067383,"slug":"shadow-of-war","type":"tag","pagerank":0.0013219723251297242,"size":5}},{"key":"99","attributes":{"label":"Star Wars Battlefront II","x":-2.6769967079162598,"y":13.281668663024902,"slug":"star-wars-battlefront-ii","type":"tag","pagerank":0.0013219723251297242,"size":5}},{"key":"100","attributes":{"label":"Battle pass","x":2.8062264919281006,"y":9.402633666992188,"slug":"battle-pass","type":"tag","pagerank":0.0013219723251297242,"size":5}}],"edges":[{"source":"89","target":"59"},{"source":"59","target":"56"},{"source":"59","target":"60"},{"source":"59","target":"61"},{"source":"59","target":"62"},{"source":"59","target":"63"},{"source":"59","target":"64"},{"source":"59","target":"65"},{"source":"59","target":"66"},{"source":"59","target":"67"},{"source":"59","target":"68"},{"source":"59","target":"69"},{"source":"59","target":"70"},{"source":"59","target":"71"},{"source":"59","target":"72"},{"source":"59","target":"73"},{"source":"59","target":"74"},{"source":"59","target":"75"},{"source":"59","target":"76"},{"source":"59","target":"77"},{"source":"59","target":"78"},{"source":"59","target":"79"},{"source":"59","target":"80"},{"source":"59","target":"81"},{"source":"59","target":"82"},{"source":"59","target":"83"},{"source":"59","target":"84"},{"source":"59","target":"85"},{"source":"59","target":"86"},{"source":"59","target":"87"},{"source":"59","target":"88"},{"source":"59","target":"89"},{"source":"59","target":"90"},{"source":"59","target":"91"},{"source":"59","target":"92"},{"source":"59","target":"93"},{"source":"59","target":"94"},{"source":"59","target":"95"},{"source":"59","target":"96"},{"source":"59","target":"97"},{"source":"59","target":"98"},{"source":"59","target":"99"},{"source":"59","target":"100"}],"options":{"type":"mixed","multi":false,"allowSelfLoops":true}}