{"attributes":{},"nodes":[{"key":"18","attributes":{"label":"Hight fantasy","x":-5.680237293243408,"y":-1.6452640295028687,"slug":"hight-fantasy","type":"tag"}},{"key":"12","attributes":{"label":"Ce qui rend la fantasy Witcher si Humaine","x":-0.24077880382537842,"y":-0.08910194784402847,"slug":"ce-qui-rend-la-fantasy-witcher-si-humaine","type":"ressource"}},{"key":"1","attributes":{"label":"Nostalgeek","x":5.577010154724121,"y":6.830623626708984,"slug":"nostalgeek","type":"author"}},{"key":"3","attributes":{"label":"Bioshock 2","x":7.1809000968933105,"y":4.071705341339111,"slug":"bioshock-2","type":"tag"}},{"key":"13","attributes":{"label":"The Witcher","x":-7.62110710144043,"y":-5.112488269805908,"slug":"the-witcher","type":"tag"}},{"key":"14","attributes":{"label":"The Witcher 3: Wild Hunt","x":-5.618829727172852,"y":-7.3639349937438965,"slug":"the-witcher-3-wild-hunt","type":"tag"}},{"key":"15","attributes":{"label":"Andrzej Sapkowski","x":-3.4313220977783203,"y":5.922952651977539,"slug":"andrzej-sapkowski","type":"tag"}},{"key":"16","attributes":{"label":"Moralité","x":5.178512096405029,"y":-6.8980560302734375,"slug":"moralite","type":"tag"}},{"key":"17","attributes":{"label":"Héroïsme","x":-3.667371988296509,"y":8.620530128479004,"slug":"heroisme","type":"tag"}},{"key":"19","attributes":{"label":"Low fantasy","x":-9.44022274017334,"y":-0.5738008618354797,"slug":"low-fantasy","type":"tag"}},{"key":"20","attributes":{"label":"Le Seigneur des Anneaux","x":-2.658627986907959,"y":-7.422871112823486,"slug":"le-seigneur-des-anneaux","type":"tag"}},{"key":"21","attributes":{"label":"Open world","x":2.6448349952697754,"y":7.044607639312744,"slug":"open-world","type":"tag"}},{"key":"22","attributes":{"label":"Paternité","x":-8.053586959838867,"y":2.6682615280151367,"slug":"paternite","type":"tag"}},{"key":"23","attributes":{"label":"Maternité","x":2.4834117889404297,"y":-7.819567680358887,"slug":"maternite","type":"tag"}},{"key":"24","attributes":{"label":"Univers","x":6.812603950500488,"y":-4.5069193840026855,"slug":"univers","type":"tag"}},{"key":"25","attributes":{"label":"Neil Gaiman","x":8.178471565246582,"y":-1.9413331747055054,"slug":"neil-gaiman","type":"tag"}},{"key":"26","attributes":{"label":"The Last of Us","x":0.1246546059846878,"y":8.784027099609375,"slug":"the-last-of-us","type":"tag"}},{"key":"27","attributes":{"label":"Dishonored","x":-0.2580971121788025,"y":-8.949884414672852,"slug":"dishonored","type":"tag"}},{"key":"28","attributes":{"label":"God of War","x":-7.108510971069336,"y":5.640384197235107,"slug":"god-of-war","type":"tag"}},{"key":"29","attributes":{"label":"Death Stranding","x":8.359260559082031,"y":1.1389636993408203,"slug":"death-stranding","type":"tag"}}],"edges":[{"source":"18","target":"12"},{"source":"12","target":"1"},{"source":"12","target":"3"},{"source":"12","target":"13"},{"source":"12","target":"14"},{"source":"12","target":"15"},{"source":"12","target":"16"},{"source":"12","target":"17"},{"source":"12","target":"18"},{"source":"12","target":"19"},{"source":"12","target":"20"},{"source":"12","target":"21"},{"source":"12","target":"22"},{"source":"12","target":"23"},{"source":"12","target":"24"},{"source":"12","target":"25"},{"source":"12","target":"26"},{"source":"12","target":"27"},{"source":"12","target":"28"},{"source":"12","target":"29"}],"options":{"type":"mixed","multi":false,"allowSelfLoops":true}}