{"attributes":{},"nodes":[{"key":"444","attributes":{"label":"Game studies","slug":"game-studies","cat":"tag","size":11,"x":-5,"y":-1}},{"key":"441","attributes":{"label":"Game studies ou études du play ?","slug":"game-studies-ou-etudes-du-play","cat":"ressource","size":9,"x":0,"y":0}},{"key":"442","attributes":{"label":"Mathieu Triclot","slug":"mathieu-triclot","cat":"author","size":7,"x":-9,"y":3}},{"key":"443","attributes":{"label":"Jesper Juul","slug":"jesper-juul","cat":"tag","size":6,"x":7,"y":-4}},{"key":"677","attributes":{"label":"Les jeux vidéo nous font-ils aimer la violence ?","slug":"les-jeux-video-nous-font-ils-aimer-la-violence","cat":"ressource","size":10,"x":0,"y":5}},{"key":"600","attributes":{"label":"Le jeu","slug":"le-jeu-jacques-henriot","cat":"ressource","size":12,"x":1,"y":-4}},{"key":"601","attributes":{"label":"Jacques Henriot","slug":"jacques-henriot","cat":"author","size":9,"x":5,"y":-1}},{"key":"761","attributes":{"label":"Philosophie des jeux vidéo","slug":"philosophie-des-jeux-video","cat":"ressource","size":8,"x":-6,"y":4}}],"edges":[{"key":"geid_683_0","source":"444","target":"441"},{"key":"geid_683_1","source":"441","target":"442"},{"key":"geid_683_2","source":"441","target":"443"},{"key":"geid_683_3","source":"441","target":"444"},{"key":"geid_683_5","source":"441","target":"677"},{"key":"geid_683_6","source":"441","target":"600"},{"key":"geid_683_7","source":"441","target":"601"},{"key":"geid_683_8","source":"444","target":"600"},{"key":"geid_683_9","source":"600","target":"441"},{"key":"geid_683_10","source":"600","target":"444"},{"key":"geid_683_11","source":"600","target":"601"},{"key":"geid_683_12","source":"600","target":"677"},{"key":"geid_683_13","source":"444","target":"761"},{"key":"geid_683_14","source":"761","target":"442"},{"key":"geid_683_15","source":"761","target":"444"},{"key":"geid_683_16","source":"761","target":"677"}],"options":{"type":"mixed","multi":false,"allowSelfLoops":true}}