{"attributes":{},"nodes":[{"key":"230","attributes":{"label":"Embargo","x":-3.9578866958618164,"y":1.5040231943130493,"slug":"embargo","type":"tag"}},{"key":"227","attributes":{"label":"Un peu de Contexte : Les tests de jeux vidéo, Metacritic : un score pour les gouverner tous","x":0.17322437465190887,"y":-0.04593552649021149,"slug":"un-peu-de-contexte-les-tests-de-jeux-video-metacritic-un-score-pour-les-gouverner-tous","type":"ressource"}},{"key":"65","attributes":{"label":"Sony","x":-5.0684123039245605,"y":-2.4745447635650635,"slug":"sony","type":"tag"}},{"key":"142","attributes":{"label":"Journalisme","x":-2.125476837158203,"y":5.218405723571777,"slug":"journalisme","type":"tag"}},{"key":"149","attributes":{"label":"Industrie","x":4.987081527709961,"y":2.3146276473999023,"slug":"industrie","type":"tag"}},{"key":"201","attributes":{"label":"Ex Serv","x":1.9601325988769531,"y":5.102036476135254,"slug":"ex-serv","type":"author"}},{"key":"228","attributes":{"label":"Metacritic","x":2.1122593879699707,"y":-5.050542831420898,"slug":"metacritic","type":"tag"}},{"key":"229","attributes":{"label":"Test","x":4.963499069213867,"y":-1.932489037513733,"slug":"test","type":"tag"}},{"key":"231","attributes":{"label":"Cyberpunk 2077","x":-1.9907236099243164,"y":-5.131312370300293,"slug":"cyberpunk-2077","type":"tag"}}],"edges":[{"source":"230","target":"227"},{"source":"227","target":"65"},{"source":"227","target":"142"},{"source":"227","target":"149"},{"source":"227","target":"201"},{"source":"227","target":"228"},{"source":"227","target":"229"},{"source":"227","target":"230"},{"source":"227","target":"231"}],"options":{"type":"mixed","multi":false,"allowSelfLoops":true}}