{"attributes":{},"nodes":[{"key":"111","attributes":{"label":"Vision d'auteur","x":4.397210597991943,"y":4.680784702301025,"slug":"vision-dauteur","type":"tag"}},{"key":"110","attributes":{"label":"Death Stranding : Repenser le Fun","x":-0.1347474306821823,"y":0.10151106864213943,"slug":"death-stranding-repenser-le-fun","type":"ressource"}},{"key":"1","attributes":{"label":"NostalGeek","x":-10.344775199890137,"y":-0.14506226778030396,"slug":"nostalgeek","type":"author"}},{"key":"21","attributes":{"label":"Open world","x":-8.748369216918945,"y":4.541394233703613,"slug":"open-world","type":"tag"}},{"key":"29","attributes":{"label":"Death Stranding","x":1.6741933822631836,"y":9.776206970214844,"slug":"death-stranding","type":"tag"}},{"key":"34","attributes":{"label":"Dark Souls","x":-7.762383937835693,"y":1.7760556936264038,"slug":"dark-souls","type":"tag"}},{"key":"102","attributes":{"label":"Hideo Kojima","x":8.421688079833984,"y":5.299930572509766,"slug":"hideo-kojima","type":"tag"}},{"key":"105","attributes":{"label":"Metal Gear","x":4.621907711029053,"y":8.512969017028809,"slug":"metal-gear","type":"tag"}},{"key":"107","attributes":{"label":"Sony","x":-3.986907958984375,"y":7.9235711097717285,"slug":"sony","type":"tag"}},{"key":"112","attributes":{"label":"Fun","x":-1.2290680408477783,"y":8.762553215026855,"slug":"fun","type":"tag"}},{"key":"113","attributes":{"label":"Collaboration","x":9.643231391906738,"y":1.8755080699920654,"slug":"collaboration","type":"tag"}},{"key":"114","attributes":{"label":"Contemplation","x":4.874804973602295,"y":-6.287252426147461,"slug":"contemplation","type":"tag"}},{"key":"115","attributes":{"label":"Accomplissement","x":7.720770359039307,"y":-5.671051502227783,"slug":"accomplissement","type":"tag"}},{"key":"116","attributes":{"label":"Dragon's dogma","x":-0.2939683496952057,"y":-10.593291282653809,"slug":"dragons-dogma","type":"tag"}},{"key":"117","attributes":{"label":"Guerilla Games","x":1.1982094049453735,"y":-7.968037128448486,"slug":"guerilla-games","type":"tag"}},{"key":"118","attributes":{"label":"Gone Home","x":-4.276883125305176,"y":-9.715660095214844,"slug":"gone-home","type":"tag"}},{"key":"119","attributes":{"label":"The Legend of Zelda: Breath of the Wild","x":-9.389877319335938,"y":-4.2705183029174805,"slug":"the-legend-of-zelda-breath-of-the-wild","type":"tag"}},{"key":"120","attributes":{"label":"Level design","x":-6.95249080657959,"y":-2.7907583713531494,"slug":"level-design","type":"tag"}},{"key":"121","attributes":{"label":"Firewatch","x":4.5039753913879395,"y":-9.458990097045898,"slug":"firewatch","type":"tag"}},{"key":"122","attributes":{"label":"What Remains of Edith Finch","x":9.554491996765137,"y":-3.063559055328369,"slug":"what-remains-of-edith-finch","type":"tag"}},{"key":"123","attributes":{"label":"Walking Simulator","x":7.832942008972168,"y":-0.6203234195709229,"slug":"walking-simulator","type":"tag"}},{"key":"124","attributes":{"label":"Jeu indépendant","x":-2.94549560546875,"y":-7.046043872833252,"slug":"jeu-independant","type":"tag"}},{"key":"125","attributes":{"label":"Triple A","x":-6.602899074554443,"y":6.747467994689941,"slug":"triple-a","type":"tag"}},{"key":"126","attributes":{"label":"Decima (Moteur de jeu)","x":-6.775036811828613,"y":-6.919521331787109,"slug":"decima-moteur-de-jeu","type":"tag"}}],"edges":[{"source":"111","target":"110"},{"source":"110","target":"1"},{"source":"110","target":"21"},{"source":"110","target":"29"},{"source":"110","target":"34"},{"source":"110","target":"102"},{"source":"110","target":"105"},{"source":"110","target":"107"},{"source":"110","target":"111"},{"source":"110","target":"112"},{"source":"110","target":"113"},{"source":"110","target":"114"},{"source":"110","target":"115"},{"source":"110","target":"116"},{"source":"110","target":"117"},{"source":"110","target":"118"},{"source":"110","target":"119"},{"source":"110","target":"120"},{"source":"110","target":"121"},{"source":"110","target":"122"},{"source":"110","target":"123"},{"source":"110","target":"124"},{"source":"110","target":"125"},{"source":"110","target":"126"}],"options":{"type":"mixed","multi":false,"allowSelfLoops":true}}