{"attributes":{},"nodes":[{"key":"153","attributes":{"label":"Level design","slug":"level-design","cat":"tag","size":11,"x":-8,"y":8}},{"key":"145","attributes":{"label":"Comment Hitman fait une critique sociale grâce à son Gameplay","slug":"comment-hitman-fait-une-critique-sociale-grace-a-son-gameplay","cat":"ressource","size":11,"x":-51,"y":25}},{"key":"1","attributes":{"label":"Toujours Thomas","slug":"toujours-thomas","cat":"author","size":12,"x":-33,"y":39}},{"key":"146","attributes":{"label":"Classe sociale","slug":"classe-sociale","cat":"tag","size":6,"x":-61,"y":33}},{"key":"147","attributes":{"label":"Critique","slug":"critique","cat":"tag","size":6,"x":-58,"y":33}},{"key":"148","attributes":{"label":"Curiosité","slug":"curiosite","cat":"tag","size":6,"x":-60,"y":27}},{"key":"151","attributes":{"label":"Hitman","slug":"hitman","cat":"tag","size":6,"x":-59,"y":-1}},{"key":"152","attributes":{"label":"Infiltration","slug":"infiltration","cat":"tag","size":6,"x":-63,"y":29}},{"key":"154","attributes":{"label":"Tourisme virtuel","slug":"tourisme-virtuel","cat":"tag","size":7,"x":-59,"y":30}},{"key":"155","attributes":{"label":"Vie quotidienne","slug":"vie-quotidienne","cat":"tag","size":6,"x":-63,"y":26}},{"key":"235","attributes":{"label":"Death Stranding : Repenser le Fun","slug":"death-stranding-repenser-le-fun","cat":"ressource","size":18,"x":3,"y":-49}},{"key":"4","attributes":{"label":"Contemplation","slug":"contemplation","cat":"tag","size":7,"x":5,"y":-65}},{"key":"15","attributes":{"label":"NostalGeek","slug":"nostalgeek","cat":"author","size":25,"x":2,"y":-3}},{"key":"24","attributes":{"label":"Dark Souls","slug":"dark-souls","cat":"tag","size":13,"x":-4,"y":-23}},{"key":"25","attributes":{"label":"Dragon's Dogma","slug":"dragons-dogma","cat":"tag","size":6,"x":5,"y":-59}},{"key":"33","attributes":{"label":"Open world","slug":"open-world","cat":"tag","size":13,"x":12,"y":-31}},{"key":"38","attributes":{"label":"The Legend of Zelda: Breath of the Wild","slug":"the-legend-of-zelda-breath-of-the-wild","cat":"tag","size":10,"x":3,"y":-62}},{"key":"87","attributes":{"label":"Death Stranding","slug":"death-stranding","cat":"tag","size":8,"x":2,"y":-65}},{"key":"108","attributes":{"label":"Fun","slug":"fun","cat":"tag","size":7,"x":9,"y":-58}},{"key":"230","attributes":{"label":"Hideo Kojima","slug":"hideo-kojima","cat":"tag","size":6,"x":9,"y":-64}},{"key":"232","attributes":{"label":"Metal Gear","slug":"metal-gear","cat":"tag","size":7,"x":-3,"y":-61}},{"key":"233","attributes":{"label":"Sony","slug":"sony","cat":"tag","size":10,"x":24,"y":-30}},{"key":"237","attributes":{"label":"Collaboration","slug":"collaboration","cat":"tag","size":6,"x":-5,"y":-59}},{"key":"239","attributes":{"label":"Firewatch","slug":"firewatch","cat":"tag","size":6,"x":12,"y":-58}},{"key":"240","attributes":{"label":"Gone Home","slug":"gone-home","cat":"tag","size":6,"x":-1,"y":-64}},{"key":"241","attributes":{"label":"Guerilla Games","slug":"guerilla-games","cat":"tag","size":6,"x":-2,"y":-57}},{"key":"242","attributes":{"label":"Jeu indépendant","slug":"jeu-independant","cat":"tag","size":6,"x":11,"y":-61}},{"key":"243","attributes":{"label":"Triple A","slug":"triple-a","cat":"tag","size":10,"x":28,"y":-40}},{"key":"244","attributes":{"label":"Vision d'auteur","slug":"vision-dauteur","cat":"tag","size":6,"x":7,"y":-61}},{"key":"245","attributes":{"label":"Walking Simulator","slug":"walking-simulator","cat":"tag","size":6,"x":1,"y":-59}},{"key":"246","attributes":{"label":"What Remains of Edith Finch","slug":"what-remains-of-edith-finch","cat":"tag","size":6,"x":-28,"y":-45}},{"key":"247","attributes":{"label":"Demon's Souls, l'Episode Oublié","slug":"demons-souls-lepisode-oublie","cat":"ressource","size":13,"x":15,"y":-9}},{"key":"125","attributes":{"label":"Bloodborne","slug":"bloodborne","cat":"tag","size":8,"x":17,"y":-18}},{"key":"131","attributes":{"label":"From Software","slug":"from-software","cat":"tag","size":9,"x":21,"y":-17}},{"key":"133","attributes":{"label":"Hidetaka Miyazaki","slug":"hidetaka-miyazaki","cat":"tag","size":9,"x":23,"y":-9}},{"key":"248","attributes":{"label":"Apocalypse","slug":"apocalypse","cat":"tag","size":5,"x":23,"y":-12}},{"key":"250","attributes":{"label":"Demon's Souls","slug":"demons-souls","cat":"tag","size":7,"x":21,"y":1}},{"key":"251","attributes":{"label":"Fumito Ueda","slug":"fumito-ueda","cat":"tag","size":6,"x":21,"y":-14}},{"key":"252","attributes":{"label":"Ico","slug":"ico","cat":"tag","size":6,"x":14,"y":-17}},{"key":"253","attributes":{"label":"PlayStation 3","slug":"playstation-3","cat":"tag","size":8,"x":33,"y":-17}},{"key":"254","attributes":{"label":"PlayStation 5","slug":"playstation-5","cat":"tag","size":7,"x":34,"y":-14}},{"key":"255","attributes":{"label":"Remake","slug":"remake","cat":"tag","size":8,"x":-4,"y":-3}},{"key":"876","attributes":{"label":"Remakes & Remasters, bons ou mauvais ?","slug":"remakes-and-remasters-bons-ou-mauvais","cat":"ressource","size":18,"x":19,"y":12}},{"key":"285","attributes":{"label":"ECHO, l'infini et la peur de l'inconnu","slug":"echo-linfini-et-la-peur-de-linconnu","cat":"ressource","size":10,"x":-6,"y":46}},{"key":"132","attributes":{"label":"H.P. Lovecraft","slug":"hp-lovecraft","cat":"tag","size":6,"x":-4,"y":59}},{"key":"134","attributes":{"label":"Horreur","slug":"horreur","cat":"tag","size":8,"x":-5,"y":55}},{"key":"136","attributes":{"label":"Horreur cosmique","slug":"horreur-cosmique","cat":"tag","size":6,"x":-2,"y":56}},{"key":"286","attributes":{"label":"Architecture","slug":"architecture","cat":"tag","size":6,"x":-13,"y":57}},{"key":"289","attributes":{"label":"Peur","slug":"peur","cat":"tag","size":7,"x":10,"y":54}},{"key":"290","attributes":{"label":"Peur de l'inconnu","slug":"peur-de-linconnu","cat":"tag","size":6,"x":10,"y":51}},{"key":"399","attributes":{"label":"Final Fantasy VII REMAKE, l'Imparfait Prologue","slug":"final-fantasy-vii-remake-imparfait-prologue","cat":"ressource","size":11,"x":-30,"y":4}},{"key":"16","attributes":{"label":"Action RPG","slug":"action-rpg","cat":"tag","size":9,"x":-37,"y":7}},{"key":"31","attributes":{"label":"Musique","slug":"musique","cat":"tag","size":10,"x":-36,"y":10}},{"key":"37","attributes":{"label":"Système de combat","slug":"systeme-de-combat","cat":"tag","size":9,"x":-40,"y":9}},{"key":"179","attributes":{"label":"Game design","slug":"game-design","cat":"tag","size":13,"x":-37,"y":-15}},{"key":"401","attributes":{"label":"Final Fantasy","slug":"final-fantasy","cat":"tag","size":8,"x":-41,"y":3}},{"key":"403","attributes":{"label":"Final Fantasy VII Remake","slug":"final-fantasy-vii-remake","cat":"tag","size":6,"x":-38,"y":0}},{"key":"404","attributes":{"label":"JRPG","slug":"jrpg","cat":"tag","size":6,"x":-38,"y":4}},{"key":"408","attributes":{"label":"Square Enix","slug":"square-enix","cat":"tag","size":7,"x":-41,"y":6}},{"key":"552","attributes":{"label":"Le Game Design de la CONNAISSANCE","slug":"le-game-design-de-la-connaissance","cat":"ressource","size":17,"x":-53,"y":-29}},{"key":"157","attributes":{"label":"Hugo (GND)","slug":"hugo-gnd","cat":"author","size":15,"x":-56,"y":-39}},{"key":"158","attributes":{"label":"Maxime (GND)","slug":"maxime-gnd","cat":"author","size":14,"x":-67,"y":-29}},{"key":"188","attributes":{"label":"Progression","slug":"progression","cat":"tag","size":7,"x":-63,"y":-36}},{"key":"191","attributes":{"label":"Rogue lite","slug":"rogue-lite","cat":"tag","size":7,"x":-61,"y":-33}},{"key":"506","attributes":{"label":"Outer Wilds","slug":"outer-wilds","cat":"tag","size":7,"x":-64,"y":-26}},{"key":"524","attributes":{"label":"Inside","slug":"inside","cat":"tag","size":6,"x":-59,"y":-41}},{"key":"555","attributes":{"label":"Boucle temporelle","slug":"boucle-temporelle","cat":"tag","size":6,"x":-65,"y":-39}},{"key":"556","attributes":{"label":"Connaissance","slug":"connaissance","cat":"tag","size":6,"x":-65,"y":-33}},{"key":"559","attributes":{"label":"Hollow Knight","slug":"hollow-knight","cat":"tag","size":6,"x":-63,"y":-29}},{"key":"561","attributes":{"label":"NieR Automata","slug":"nier-automata","cat":"tag","size":6,"x":-62,"y":-40}},{"key":"564","attributes":{"label":"Portal","slug":"portal","cat":"tag","size":6,"x":-68,"y":-32}},{"key":"565","attributes":{"label":"Prey","slug":"prey","cat":"tag","size":6,"x":-67,"y":-36}},{"key":"566","attributes":{"label":"Rejouabilité","slug":"rejouabilite","cat":"tag","size":6,"x":-59,"y":-37}},{"key":"722","attributes":{"label":"Percer les Murs de Control","slug":"percer-les-murs-de-control","cat":"ressource","size":15,"x":-22,"y":54}},{"key":"5","attributes":{"label":"Direction artistique","slug":"direction-artistique","cat":"tag","size":10,"x":-2,"y":36}},{"key":"32","attributes":{"label":"Mythologie nordique","slug":"mythologie-nordique","cat":"tag","size":7,"x":-28,"y":68}},{"key":"351","attributes":{"label":"Control (jeu)","slug":"control-jeu","cat":"tag","size":6,"x":-31,"y":65}},{"key":"469","attributes":{"label":"Art","slug":"art","cat":"tag","size":7,"x":-21,"y":64}},{"key":"584","attributes":{"label":"Normalité","slug":"normalite","cat":"tag","size":6,"x":-21,"y":68}},{"key":"624","attributes":{"label":"Les Fantômes de Kentucky Route Zero","slug":"les-fantomes-de-kentucky-route-zero","cat":"ressource","size":12,"x":-28,"y":64}},{"key":"638","attributes":{"label":"Hyperréalité","slug":"hyperrealite","cat":"tag","size":6,"x":-33,"y":62}},{"key":"640","attributes":{"label":"Jean Baudrillard","slug":"jean-baudrillard","cat":"tag","size":6,"x":-25,"y":69}},{"key":"644","attributes":{"label":"Simulacres et simulation","slug":"simulacres-et-simulation","cat":"tag","size":6,"x":-25,"y":62}},{"key":"682","attributes":{"label":"Esthétique","slug":"esthetique","cat":"tag","size":6,"x":-32,"y":59}},{"key":"724","attributes":{"label":"Brutalisme","slug":"brutalisme","cat":"tag","size":6,"x":-24,"y":66}},{"key":"735","attributes":{"label":"Surnaturelle","slug":"surnaturelle","cat":"tag","size":6,"x":-29,"y":60}},{"key":"865","attributes":{"label":"RÉINVENTER METROID (Metroid Dread) | Video Games Lab #6","slug":"reinventer-metroid-metroid-dread-video-games-lab-6","cat":"ressource","size":11,"x":21,"y":45}},{"key":"6","attributes":{"label":"Exploration","slug":"exploration","cat":"tag","size":11,"x":42,"y":18}},{"key":"126","attributes":{"label":"Boss","slug":"boss","cat":"tag","size":6,"x":31,"y":55}},{"key":"360","attributes":{"label":"Metroid","slug":"metroid","cat":"tag","size":6,"x":30,"y":52}},{"key":"429","attributes":{"label":"Metroidvania","slug":"metroidvania","cat":"tag","size":6,"x":27,"y":54}},{"key":"431","attributes":{"label":"Plateformer 2D","slug":"plateformer-2d","cat":"tag","size":6,"x":28,"y":57}},{"key":"608","attributes":{"label":"At0mium","slug":"at0mium","cat":"author","size":7,"x":25,"y":57}},{"key":"28","attributes":{"label":"Graphisme","slug":"graphisme","cat":"tag","size":8,"x":40,"y":0}},{"key":"46","attributes":{"label":"Folie","slug":"folie","cat":"tag","size":7,"x":24,"y":24}},{"key":"59","attributes":{"label":"Call of Duty","slug":"call-of-duty","cat":"tag","size":8,"x":32,"y":16}},{"key":"89","attributes":{"label":"God of War","slug":"god-of-war","cat":"tag","size":7,"x":22,"y":20}},{"key":"98","attributes":{"label":"The Last of Us","slug":"the-last-of-us","cat":"tag","size":7,"x":37,"y":-2}},{"key":"109","attributes":{"label":"Gameplay","slug":"gameplay","cat":"tag","size":10,"x":27,"y":15}},{"key":"112","attributes":{"label":"Nostalgie","slug":"nostalgie","cat":"tag","size":7,"x":28,"y":18}},{"key":"264","attributes":{"label":"Industrie","slug":"industrie","cat":"tag","size":10,"x":27,"y":23}},{"key":"275","attributes":{"label":"Remaster","slug":"remaster","cat":"tag","size":5,"x":30,"y":13}},{"key":"379","attributes":{"label":"Resident Evil 2","slug":"resident-evil-2","cat":"tag","size":6,"x":30,"y":22}},{"key":"531","attributes":{"label":"Skyrim","slug":"skyrim","cat":"tag","size":7,"x":2,"y":1}},{"key":"705","attributes":{"label":"Shadow of the Colossus","slug":"shadow-of-the-colossus","cat":"tag","size":6,"x":32,"y":19}},{"key":"767","attributes":{"label":"Microtransaction","slug":"microtransaction","cat":"tag","size":6,"x":17,"y":21}},{"key":"768","attributes":{"label":"Modèle économique","slug":"modele-economique","cat":"tag","size":6,"x":20,"y":23}},{"key":"777","attributes":{"label":"Éditeur de jeux vidéo","slug":"editeur-de-jeux-video","cat":"tag","size":6,"x":25,"y":19}},{"key":"896","attributes":{"label":"Skyblivion ou le futur du Modding","slug":"skyblivion-ou-le-futur-du-modding","cat":"ressource","size":13,"x":-15,"y":-14}},{"key":"256","attributes":{"label":"Diablo II Resurrected, Respecter un Héritage","slug":"diablo-ii-resurrected-respecter-un-heritage","cat":"ressource","size":16,"x":-19,"y":-21}},{"key":"332","attributes":{"label":"Jeu de rôle (RPG)","slug":"jeu-de-role-rpg","cat":"tag","size":9,"x":-16,"y":-23}},{"key":"779","attributes":{"label":"Bethesda","slug":"bethesda","cat":"tag","size":6,"x":-23,"y":-15}},{"key":"783","attributes":{"label":"Morrowind","slug":"morrowind","cat":"tag","size":6,"x":-21,"y":-18}},{"key":"784","attributes":{"label":"Oblivion","slug":"oblivion","cat":"tag","size":6,"x":-24,"y":-20}},{"key":"785","attributes":{"label":"The Elder Scrolls","slug":"the-elder-scrolls","cat":"tag","size":6,"x":-22,"y":-23}},{"key":"897","attributes":{"label":"Modding","slug":"modding","cat":"tag","size":6,"x":-19,"y":-25}},{"key":"960","attributes":{"label":"The Last of Us 2, la Suite Superflue","slug":"the-last-of-us-2-la-suite-superflue","cat":"ressource","size":18,"x":45,"y":-17}},{"key":"48","attributes":{"label":"Narration","slug":"narration","cat":"tag","size":13,"x":58,"y":-19}},{"key":"121","attributes":{"label":"Alien: Isolation","slug":"alien-isolation","cat":"tag","size":7,"x":55,"y":-20}},{"key":"260","attributes":{"label":"Crunch","slug":"crunch","cat":"tag","size":7,"x":54,"y":-24}},{"key":"284","attributes":{"label":"Uncharted 4","slug":"uncharted-4","cat":"tag","size":6,"x":61,"y":-23}},{"key":"306","attributes":{"label":"PlayStation 4","slug":"playstation-4","cat":"tag","size":7,"x":56,"y":-28}},{"key":"421","attributes":{"label":"Naughty Dog","slug":"naughty-dog","cat":"tag","size":6,"x":56,"y":-16}},{"key":"448","attributes":{"label":"Histoire","slug":"histoire","cat":"tag","size":8,"x":57,"y":-13}},{"key":"538","attributes":{"label":"Intelligence artificielle","slug":"intelligence-artificielle","cat":"tag","size":7,"x":52,"y":-26}},{"key":"772","attributes":{"label":"Rockstar Games","slug":"rockstar-games","cat":"tag","size":6,"x":60,"y":-15}},{"key":"775","attributes":{"label":"The Last of Us Part II","slug":"the-last-of-us-part-ii","cat":"tag","size":6,"x":61,"y":-19}},{"key":"786","attributes":{"label":"Végétagion","slug":"vegetagion","cat":"tag","size":5,"x":57,"y":-23}},{"key":"968","attributes":{"label":"Suite","slug":"suite","cat":"tag","size":5,"x":52,"y":-29}},{"key":"281","attributes":{"label":"Jason Schreier","slug":"jason-schreier","cat":"author","size":7,"x":59,"y":-26}}],"edges":[{"key":"geid_392_0","source":"153","target":"145"},{"key":"geid_392_1","source":"145","target":"1"},{"key":"geid_392_2","source":"145","target":"146"},{"key":"geid_392_3","source":"145","target":"147"},{"key":"geid_392_4","source":"145","target":"148"},{"key":"geid_392_7","source":"145","target":"151"},{"key":"geid_392_8","source":"145","target":"152"},{"key":"geid_392_9","source":"145","target":"153"},{"key":"geid_392_10","source":"145","target":"154"},{"key":"geid_392_11","source":"145","target":"155"},{"key":"geid_392_12","source":"153","target":"235"},{"key":"geid_392_13","source":"235","target":"4"},{"key":"geid_392_14","source":"235","target":"15"},{"key":"geid_392_15","source":"235","target":"24"},{"key":"geid_392_16","source":"235","target":"25"},{"key":"geid_392_17","source":"235","target":"33"},{"key":"geid_392_18","source":"235","target":"38"},{"key":"geid_392_19","source":"235","target":"87"},{"key":"geid_392_20","source":"235","target":"108"},{"key":"geid_392_21","source":"235","target":"153"},{"key":"geid_392_22","source":"235","target":"230"},{"key":"geid_392_23","source":"235","target":"232"},{"key":"geid_392_24","source":"235","target":"233"},{"key":"geid_392_26","source":"235","target":"237"},{"key":"geid_392_28","source":"235","target":"239"},{"key":"geid_392_29","source":"235","target":"240"},{"key":"geid_392_30","source":"235","target":"241"},{"key":"geid_392_31","source":"235","target":"242"},{"key":"geid_392_32","source":"235","target":"243"},{"key":"geid_392_33","source":"235","target":"244"},{"key":"geid_392_34","source":"235","target":"245"},{"key":"geid_392_35","source":"235","target":"246"},{"key":"geid_392_36","source":"153","target":"247"},{"key":"geid_392_37","source":"247","target":"15"},{"key":"geid_392_38","source":"247","target":"24"},{"key":"geid_392_39","source":"247","target":"125"},{"key":"geid_392_40","source":"247","target":"131"},{"key":"geid_392_41","source":"247","target":"133"},{"key":"geid_392_42","source":"247","target":"153"},{"key":"geid_392_43","source":"247","target":"233"},{"key":"geid_392_44","source":"247","target":"248"},{"key":"geid_392_46","source":"247","target":"250"},{"key":"geid_392_47","source":"247","target":"251"},{"key":"geid_392_48","source":"247","target":"252"},{"key":"geid_392_49","source":"247","target":"253"},{"key":"geid_392_50","source":"247","target":"254"},{"key":"geid_392_51","source":"247","target":"255"},{"key":"geid_392_52","source":"247","target":"876"},{"key":"geid_392_53","source":"153","target":"285"},{"key":"geid_392_54","source":"285","target":"1"},{"key":"geid_392_55","source":"285","target":"132"},{"key":"geid_392_56","source":"285","target":"134"},{"key":"geid_392_57","source":"285","target":"136"},{"key":"geid_392_58","source":"285","target":"153"},{"key":"geid_392_59","source":"285","target":"286"},{"key":"geid_392_62","source":"285","target":"289"},{"key":"geid_392_63","source":"285","target":"290"},{"key":"geid_392_66","source":"153","target":"399"},{"key":"geid_392_67","source":"399","target":"15"},{"key":"geid_392_68","source":"399","target":"16"},{"key":"geid_392_69","source":"399","target":"31"},{"key":"geid_392_70","source":"399","target":"37"},{"key":"geid_392_71","source":"399","target":"153"},{"key":"geid_392_72","source":"399","target":"179"},{"key":"geid_392_73","source":"399","target":"255"},{"key":"geid_392_75","source":"399","target":"401"},{"key":"geid_392_77","source":"399","target":"403"},{"key":"geid_392_78","source":"399","target":"404"},{"key":"geid_392_82","source":"399","target":"408"},{"key":"geid_392_84","source":"153","target":"552"},{"key":"geid_392_85","source":"552","target":"24"},{"key":"geid_392_86","source":"552","target":"151"},{"key":"geid_392_87","source":"552","target":"153"},{"key":"geid_392_88","source":"552","target":"157"},{"key":"geid_392_89","source":"552","target":"158"},{"key":"geid_392_90","source":"552","target":"179"},{"key":"geid_392_91","source":"552","target":"188"},{"key":"geid_392_92","source":"552","target":"191"},{"key":"geid_392_93","source":"552","target":"246"},{"key":"geid_392_94","source":"552","target":"506"},{"key":"geid_392_95","source":"552","target":"524"},{"key":"geid_392_98","source":"552","target":"555"},{"key":"geid_392_99","source":"552","target":"556"},{"key":"geid_392_102","source":"552","target":"559"},{"key":"geid_392_104","source":"552","target":"561"},{"key":"geid_392_107","source":"552","target":"564"},{"key":"geid_392_108","source":"552","target":"565"},{"key":"geid_392_109","source":"552","target":"566"},{"key":"geid_392_115","source":"153","target":"722"},{"key":"geid_392_116","source":"722","target":"5"},{"key":"geid_392_117","source":"722","target":"15"},{"key":"geid_392_118","source":"722","target":"32"},{"key":"geid_392_119","source":"722","target":"153"},{"key":"geid_392_120","source":"722","target":"286"},{"key":"geid_392_121","source":"722","target":"351"},{"key":"geid_392_122","source":"722","target":"469"},{"key":"geid_392_123","source":"722","target":"584"},{"key":"geid_392_124","source":"722","target":"624"},{"key":"geid_392_125","source":"722","target":"638"},{"key":"geid_392_126","source":"722","target":"640"},{"key":"geid_392_127","source":"722","target":"644"},{"key":"geid_392_128","source":"722","target":"682"},{"key":"geid_392_130","source":"722","target":"724"},{"key":"geid_392_141","source":"722","target":"735"},{"key":"geid_392_142","source":"153","target":"865"},{"key":"geid_392_143","source":"865","target":"6"},{"key":"geid_392_144","source":"865","target":"126"},{"key":"geid_392_145","source":"865","target":"153"},{"key":"geid_392_146","source":"865","target":"289"},{"key":"geid_392_147","source":"865","target":"290"},{"key":"geid_392_148","source":"865","target":"360"},{"key":"geid_392_149","source":"865","target":"429"},{"key":"geid_392_150","source":"865","target":"431"},{"key":"geid_392_151","source":"865","target":"608"},{"key":"geid_392_162","source":"153","target":"876"},{"key":"geid_392_163","source":"876","target":"5"},{"key":"geid_392_164","source":"876","target":"15"},{"key":"geid_392_165","source":"876","target":"24"},{"key":"geid_392_166","source":"876","target":"28"},{"key":"geid_392_167","source":"876","target":"46"},{"key":"geid_392_168","source":"876","target":"59"},{"key":"geid_392_169","source":"876","target":"89"},{"key":"geid_392_170","source":"876","target":"98"},{"key":"geid_392_171","source":"876","target":"109"},{"key":"geid_392_172","source":"876","target":"112"},{"key":"geid_392_173","source":"876","target":"153"},{"key":"geid_392_174","source":"876","target":"247"},{"key":"geid_392_175","source":"876","target":"250"},{"key":"geid_392_176","source":"876","target":"255"},{"key":"geid_392_177","source":"876","target":"264"},{"key":"geid_392_178","source":"876","target":"275"},{"key":"geid_392_179","source":"876","target":"379"},{"key":"geid_392_180","source":"876","target":"531"},{"key":"geid_392_181","source":"876","target":"705"},{"key":"geid_392_182","source":"876","target":"767"},{"key":"geid_392_183","source":"876","target":"768"},{"key":"geid_392_184","source":"876","target":"777"},{"key":"geid_392_189","source":"153","target":"896"},{"key":"geid_392_190","source":"896","target":"15"},{"key":"geid_392_191","source":"896","target":"33"},{"key":"geid_392_192","source":"896","target":"153"},{"key":"geid_392_193","source":"896","target":"179"},{"key":"geid_392_194","source":"896","target":"255"},{"key":"geid_392_195","source":"896","target":"256"},{"key":"geid_392_196","source":"896","target":"332"},{"key":"geid_392_197","source":"896","target":"531"},{"key":"geid_392_198","source":"896","target":"779"},{"key":"geid_392_199","source":"896","target":"783"},{"key":"geid_392_200","source":"896","target":"784"},{"key":"geid_392_201","source":"896","target":"785"},{"key":"geid_392_202","source":"896","target":"897"},{"key":"geid_392_206","source":"153","target":"960"},{"key":"geid_392_207","source":"960","target":"6"},{"key":"geid_392_208","source":"960","target":"15"},{"key":"geid_392_209","source":"960","target":"28"},{"key":"geid_392_210","source":"960","target":"33"},{"key":"geid_392_211","source":"960","target":"48"},{"key":"geid_392_212","source":"960","target":"98"},{"key":"geid_392_213","source":"960","target":"121"},{"key":"geid_392_214","source":"960","target":"153"},{"key":"geid_392_215","source":"960","target":"233"},{"key":"geid_392_216","source":"960","target":"243"},{"key":"geid_392_217","source":"960","target":"253"},{"key":"geid_392_218","source":"960","target":"254"},{"key":"geid_392_219","source":"960","target":"260"},{"key":"geid_392_220","source":"960","target":"284"},{"key":"geid_392_221","source":"960","target":"306"},{"key":"geid_392_222","source":"960","target":"421"},{"key":"geid_392_223","source":"960","target":"448"},{"key":"geid_392_224","source":"960","target":"538"},{"key":"geid_392_225","source":"960","target":"772"},{"key":"geid_392_226","source":"960","target":"775"},{"key":"geid_392_227","source":"960","target":"786"},{"key":"geid_392_235","source":"960","target":"968"},{"key":"geid_392_238","source":"960","target":"281"}],"options":{"type":"mixed","multi":false,"allowSelfLoops":true}}