{"attributes":{},"nodes":[{"key":"290","attributes":{"label":"Skyblivion","x":-1.3185997009277344,"y":5.233635902404785,"slug":"skyblivion","type":"tag"}},{"key":"287","attributes":{"label":"Skyblivion ou le futur du Modding","x":-0.028299562633037567,"y":0.016097940504550934,"slug":"skyblivion-ou-le-futur-du-modding","type":"ressource"}},{"key":"1","attributes":{"label":"NostalGeek","x":6.271458625793457,"y":3.5564935207366943,"slug":"nostalgeek","type":"author"}},{"key":"21","attributes":{"label":"Open world","x":7.517629146575928,"y":0.6266230940818787,"slug":"open-world","type":"tag"}},{"key":"63","attributes":{"label":"Game design","x":-6.734374523162842,"y":-2.214871406555176,"slug":"game-design","type":"tag"}},{"key":"120","attributes":{"label":"Level design","x":4.3133931159973145,"y":6.229760646820068,"slug":"level-design","type":"tag"}},{"key":"131","attributes":{"label":"Remake","x":-5.10468053817749,"y":6.538124084472656,"slug":"remake","type":"tag"}},{"key":"213","attributes":{"label":"RPG","x":-2.692276954650879,"y":-7.578189373016357,"slug":"rpg","type":"tag"}},{"key":"273","attributes":{"label":"Skyrim","x":-6.220276832580566,"y":3.318878650665283,"slug":"skyrim","type":"tag"}},{"key":"288","attributes":{"label":"The Elder Scrolls","x":1.0969903469085693,"y":7.933990001678467,"slug":"the-elder-scrolls","type":"tag"}},{"key":"289","attributes":{"label":"Modding","x":-0.32243841886520386,"y":-6.095479965209961,"slug":"modding","type":"tag"}},{"key":"291","attributes":{"label":"Skywind","x":-5.659330368041992,"y":-5.391358375549316,"slug":"skywind","type":"tag"}},{"key":"292","attributes":{"label":"Oblivion","x":2.417799711227417,"y":-7.661444664001465,"slug":"oblivion","type":"tag"}},{"key":"293","attributes":{"label":"Rebelzize","x":7.053321361541748,"y":-2.9153547286987305,"slug":"rebelzize","type":"tag"}},{"key":"294","attributes":{"label":"Bethesda","x":-8.101790428161621,"y":0.6715264916419983,"slug":"bethesda","type":"tag"}},{"key":"295","attributes":{"label":"Morrowind","x":4.862672328948975,"y":-5.257999897003174,"slug":"morrowind","type":"tag"}}],"edges":[{"source":"290","target":"287"},{"source":"287","target":"1"},{"source":"287","target":"21"},{"source":"287","target":"63"},{"source":"287","target":"120"},{"source":"287","target":"131"},{"source":"287","target":"213"},{"source":"287","target":"273"},{"source":"287","target":"288"},{"source":"287","target":"289"},{"source":"287","target":"290"},{"source":"287","target":"291"},{"source":"287","target":"292"},{"source":"287","target":"293"},{"source":"287","target":"294"},{"source":"287","target":"295"}],"options":{"type":"mixed","multi":false,"allowSelfLoops":true}}